{"version":"tough-cookie@2.5.0","storeType":"MemoryCookieStore","rejectPublicSuffixes":true,"cookies":[{"key":"csrftoken","value":"cHDyBv2II5YzGz32oMlzS06pA3Dny16Y","expires":"2022-02-06T21:21:43.000Z","maxAge":31449600,"domain":"instagram.com","path":"/","secure":true,"hostOnly":false,"creation":"2021-02-07T20:03:07.896Z","lastAccessed":"2021-02-07T21:21:43.279Z"},{"key":"mid","value":"YCBHewABAAEFJYMZ41lafhTNbgtC","expires":"2023-02-07T20:03:07.000Z","maxAge":63072000,"domain":"instagram.com","path":"/","secure":true,"hostOnly":false,"creation":"2021-02-07T20:03:07.898Z","lastAccessed":"2021-02-07T21:21:36.500Z"},{"key":"ds_user","value":"funnyscreamstg","expires":"2021-05-08T20:03:10.000Z","maxAge":7776000,"domain":"instagram.com","path":"/","secure":true,"httpOnly":true,"hostOnly":false,"creation":"2021-02-07T20:03:10.976Z","lastAccessed":"2021-02-07T21:21:36.500Z"},{"key":"rur","value":"FRC","domain":"instagram.com","path":"/","secure":true,"httpOnly":true,"hostOnly":false,"creation":"2021-02-07T20:03:10.978Z","lastAccessed":"2021-02-07T21:21:43.280Z"},{"key":"ds_user_id","value":"45520950148","expires":"2021-05-08T21:21:43.000Z","maxAge":7776000,"domain":"instagram.com","path":"/","secure":true,"hostOnly":false,"creation":"2021-02-07T20:03:10.979Z","lastAccessed":"2021-02-07T21:21:43.281Z"},{"key":"sessionid","value":"45520950148%3AZSDfv8RanLRcFp%3A22","expires":"2022-02-07T20:03:10.000Z","maxAge":31536000,"domain":"instagram.com","path":"/","secure":true,"httpOnly":true,"hostOnly":false,"creation":"2021-02-07T20:03:10.980Z","lastAccessed":"2021-02-07T21:21:36.500Z"}],"state":{"deviceString":"26/8.0.0; 420dpi; 1080x1920; samsung; SM-A720F; a7y17lte; samsungexynos7880","deviceId":"android-8d2d5ef06f0b3cde","uuid":"54b8e14b-ba8d-5632-b1ac-89ab850b072c","phoneId":"46d0280f-d21e-5b49-aac4-1c6501bd1a3f","adid":"3fcd6287-dc22-514f-aa8d-a410ddaa69ee","build":"N2G48C"}}